<Bakery><compositionOfProducts><compositionOfProducts><ingredient><id>0</id><name>Ingredient</name><quantityInStock>99</quantityInStock><validityPeriod>61572693600000</validityPeriod><energyValue>284</energyValue><price>6941</price></ingredient><count>2586</count></compositionOfProducts><compositionOfProducts><ingredient><id>0</id><name>Ingredient</name><quantityInStock>172</quantityInStock><validityPeriod>61572693600000</validityPeriod><energyValue>173</energyValue><price>9387</price></ingredient><count>5330</count></compositionOfProducts><compositionOfProducts><ingredient><id>0</id><name>Ingredient</name><quantityInStock>88</quantityInStock><validityPeriod>61572693600000</validityPeriod><energyValue>186</energyValue><price>5867</price></ingredient><count>4676</count></compositionOfProducts><compositionOfProducts><ingredient><id>0</id><name>Ingredient</name><quantityInStock>36</quantityInStock><validityPeriod>61572693600000</validityPeriod><energyValue>297</energyValue><price>4878</price></ingredient><count>8608</count></compositionOfProducts><compositionOfProducts><ingredient><id>0</id><name>Ingredient</name><quantityInStock>161</quantityInStock><validityPeriod>61572693600000</validityPeriod><energyValue>163</energyValue><price>2930</price></ingredient><count>4990</count></compositionOfProducts><compositionOfProducts><ingredient><id>0</id><name>Ingredient</name><quantityInStock>197</quantityInStock><validityPeriod>61572693600000</validityPeriod><energyValue>297</energyValue><price>9794</price></ingredient><count>4782</count></compositionOfProducts><compositionOfProducts><ingredient><id>0</id><name>Ingredient</name><quantityInStock>127</quantityInStock><validityPeriod>61572693600000</validityPeriod><energyValue>163</energyValue><price>9564</price></ingredient><count>5595</count></compositionOfProducts><compositionOfProducts><ingredient><id>0</id><name>Ingredient</name><quantityInStock>49</quantityInStock><validityPeriod>61572693600000</validityPeriod><energyValue>263</energyValue><price>1798</price></ingredient><count>3245</count></compositionOfProducts><compositionOfProducts><ingredient><id>0</id><name>Ingredient</name><quantityInStock>141</quantityInStock><validityPeriod>61572693600000</validityPeriod><energyValue>300</energyValue><price>8588</price></ingredient><count>6521</count></compositionOfProducts><compositionOfProducts><ingredient><id>0</id><name>Ingredient</name><quantityInStock>62</quantityInStock><validityPeriod>61572693600000</validityPeriod><energyValue>254</energyValue><price>4256</price></ingredient><count>5500</count></compositionOfProducts></compositionOfProducts><name>Bakery</name><weight>926</weight><shelfLife>67</shelfLife><energyValue>402</energyValue><optPrice>285</optPrice></Bakery>